LICENSE.txt
MANIFEST.in
README.txt
setup.py
SimpleHist.egg-info/PKG-INFO
SimpleHist.egg-info/SOURCES.txt
SimpleHist.egg-info/dependency_links.txt
SimpleHist.egg-info/not-zip-safe
SimpleHist.egg-info/requires.txt
SimpleHist.egg-info/top_level.txt
simplehist/__init__.py
simplehist/binning.py
simplehist/hists.py
simplehist/test/__init__.py
simplehist/test/testBinning.py
simplehist/test/testHists.py
simplehist/test/testROOT.py