Metadata-Version: 1.0
Name: SimpleHist
Version: 0.1
Summary: Simple histogram classes, designed for data manipulation
Home-page: https://github.com/ndevenish/simplehistogram
Author: Nicholas Devenish
Author-email: n.e.devenish@sussex.ac.uk
License: Copyright (c) 2011 Nicholas Devenish <n.e.devenish@sussex.ac.uk>
